{
    "type": "FeatureCollection",
    "features": [
        {
            "type": "Feature",
            "properties": {
                "類別": "防空掩體",
                "電腦編號": "53.0",
                "縣市別": "連江縣",
                "鄉鎮別": "南竿鄉",
                "村里別": "津沙村",
                "地址": "120號旁津、仁步道順上約10公尺處左方",
                "地下樓層數": "1.0",
                "可容納人數": "25.0",
                "備註": ""
            },
            "geometry": {
                "type": "Point",
                "coordinates": [
                    119.91794,
                    26.14206
                ]
            }
        }
    ]
}