{
  "Info": [
    {
      "IsSuccess": "True",
      "InAddress": "彰化縣彰化市莿桐里彰鹿路35號",
      "InSRS": "EPSG:4326",
      "InFuzzyType": "[單雙號機制]+[最近門牌號機制]",
      "InFuzzyBuffer": "0",
      "InIsOnlyFullMatch": "False",
      "InIsSupportPast": "True",
      "InIsShowCodeBase": "True",
      "InIsLockCounty": "True",
      "InIsLockTown": "False",
      "InIsLockVillage": "False",
      "InIsLockRoadSection": "False",
      "InIsLockLane": "False",
      "InIsLockAlley": "False",
      "InIsLockArea": "False",
      "InIsSameNumber_SubNumber": "True",
      "InCanIgnoreVillage": "True",
      "InCanIgnoreNeighborhood": "True",
      "InReturnMaxCount": "0",
      "OutTotal": "25",
      "OutMatchType": "模糊比對",
      "OutMatchCode": "[彰化縣]\tT:1,V:1,R:1,S:-1,L:-1,A:-1,SA:-1,T:-1,AR:-1,NO:1,E:-1,N:-1",
      "OutTraceInfo": "[彰化縣]\t { 模糊比對 } (彰化市)\t找到符合的[鄉鎮市區]，(莿桐里)\t找到符合的[村里]，(彰鹿路)\t找到符合的[路街名]，(35號)\t找到符合的[門牌號碼]，進行[單號過濾]，進行[找最小門牌的號之、之號]，模糊比對找到 25 筆符合的門牌地址。( 限制回傳 10 筆門牌地址 )"
    }
  ],
  "AddressList": [
    {
      "PERIOD": "",
      "FULL_ADDR": "彰化縣彰化市莿桐里2鄰彰鹿路35號之10",
      "COUNTY": "彰化縣",
      "TOWN": "彰化市",
      "VILLAGE": "莿桐里",
      "NEIGHBORHOOD": "2鄰",
      "ROAD": "彰鹿路",
      "SECTION": "",
      "LANE": "",
      "ALLEY": "",
      "SUB_ALLEY": "",
      "TONG": "",
      "AREA": "",
      "NUMBER": "35號之10",
      "X": 120.518231,
      "Y": 24.062259,
      "CODEBASE": "A0701-1212-00",
      "CODE1": "A0701-75-004",
      "CODE2": "A0701-75"
    },
    {
      "PERIOD": "",
      "FULL_ADDR": "彰化縣彰化市莿桐里2鄰彰鹿路35號之11",
      "COUNTY": "彰化縣",
      "TOWN": "彰化市",
      "VILLAGE": "莿桐里",
      "NEIGHBORHOOD": "2鄰",
      "ROAD": "彰鹿路",
      "SECTION": "",
      "LANE": "",
      "ALLEY": "",
      "SUB_ALLEY": "",
      "TONG": "",
      "AREA": "",
      "NUMBER": "35號之11",
      "X": 120.518262,
      "Y": 24.062283,
      "CODEBASE": "A0701-1212-00",
      "CODE1": "A0701-75-004",
      "CODE2": "A0701-75"
    },
    {
      "PERIOD": "",
      "FULL_ADDR": "彰化縣彰化市莿桐里2鄰彰鹿路35號之12",
      "COUNTY": "彰化縣",
      "TOWN": "彰化市",
      "VILLAGE": "莿桐里",
      "NEIGHBORHOOD": "2鄰",
      "ROAD": "彰鹿路",
      "SECTION": "",
      "LANE": "",
      "ALLEY": "",
      "SUB_ALLEY": "",
      "TONG": "",
      "AREA": "",
      "NUMBER": "35號之12",
      "X": 120.518292,
      "Y": 24.062311,
      "CODEBASE": "A0701-1212-00",
      "CODE1": "A0701-75-004",
      "CODE2": "A0701-75"
    },
    {
      "PERIOD": "",
      "FULL_ADDR": "彰化縣彰化市莿桐里2鄰彰鹿路35號之13",
      "COUNTY": "彰化縣",
      "TOWN": "彰化市",
      "VILLAGE": "莿桐里",
      "NEIGHBORHOOD": "2鄰",
      "ROAD": "彰鹿路",
      "SECTION": "",
      "LANE": "",
      "ALLEY": "",
      "SUB_ALLEY": "",
      "TONG": "",
      "AREA": "",
      "NUMBER": "35號之13",
      "X": 120.518317,
      "Y": 24.062338,
      "CODEBASE": "A0701-1212-00",
      "CODE1": "A0701-75-004",
      "CODE2": "A0701-75"
    },
    {
      "PERIOD": "",
      "FULL_ADDR": "彰化縣彰化市莿桐里2鄰彰鹿路35號之14",
      "COUNTY": "彰化縣",
      "TOWN": "彰化市",
      "VILLAGE": "莿桐里",
      "NEIGHBORHOOD": "2鄰",
      "ROAD": "彰鹿路",
      "SECTION": "",
      "LANE": "",
      "ALLEY": "",
      "SUB_ALLEY": "",
      "TONG": "",
      "AREA": "",
      "NUMBER": "35號之14",
      "X": 120.518353,
      "Y": 24.062365,
      "CODEBASE": "A0701-1212-00",
      "CODE1": "A0701-75-004",
      "CODE2": "A0701-75"
    },
    {
      "PERIOD": "",
      "FULL_ADDR": "彰化縣彰化市莿桐里2鄰彰鹿路35號之15",
      "COUNTY": "彰化縣",
      "TOWN": "彰化市",
      "VILLAGE": "莿桐里",
      "NEIGHBORHOOD": "2鄰",
      "ROAD": "彰鹿路",
      "SECTION": "",
      "LANE": "",
      "ALLEY": "",
      "SUB_ALLEY": "",
      "TONG": "",
      "AREA": "",
      "NUMBER": "35號之15",
      "X": 120.518376,
      "Y": 24.062393,
      "CODEBASE": "A0701-1212-00",
      "CODE1": "A0701-75-004",
      "CODE2": "A0701-75"
    },
    {
      "PERIOD": "",
      "FULL_ADDR": "彰化縣彰化市莿桐里2鄰彰鹿路35號之16",
      "COUNTY": "彰化縣",
      "TOWN": "彰化市",
      "VILLAGE": "莿桐里",
      "NEIGHBORHOOD": "2鄰",
      "ROAD": "彰鹿路",
      "SECTION": "",
      "LANE": "",
      "ALLEY": "",
      "SUB_ALLEY": "",
      "TONG": "",
      "AREA": "",
      "NUMBER": "35號之16",
      "X": 120.518407,
      "Y": 24.062415,
      "CODEBASE": "A0701-1212-00",
      "CODE1": "A0701-75-004",
      "CODE2": "A0701-75"
    },
    {
      "PERIOD": "",
      "FULL_ADDR": "彰化縣彰化市莿桐里2鄰彰鹿路35號之17",
      "COUNTY": "彰化縣",
      "TOWN": "彰化市",
      "VILLAGE": "莿桐里",
      "NEIGHBORHOOD": "2鄰",
      "ROAD": "彰鹿路",
      "SECTION": "",
      "LANE": "",
      "ALLEY": "",
      "SUB_ALLEY": "",
      "TONG": "",
      "AREA": "",
      "NUMBER": "35號之17",
      "X": 120.518444,
      "Y": 24.062436,
      "CODEBASE": "A0701-1212-00",
      "CODE1": "A0701-75-004",
      "CODE2": "A0701-75"
    },
    {
      "PERIOD": "",
      "FULL_ADDR": "彰化縣彰化市莿桐里2鄰彰鹿路35號之18",
      "COUNTY": "彰化縣",
      "TOWN": "彰化市",
      "VILLAGE": "莿桐里",
      "NEIGHBORHOOD": "2鄰",
      "ROAD": "彰鹿路",
      "SECTION": "",
      "LANE": "",
      "ALLEY": "",
      "SUB_ALLEY": "",
      "TONG": "",
      "AREA": "",
      "NUMBER": "35號之18",
      "X": 120.518480,
      "Y": 24.062455,
      "CODEBASE": "A0701-1212-00",
      "CODE1": "A0701-75-004",
      "CODE2": "A0701-75"
    },
    {
      "PERIOD": "",
      "FULL_ADDR": "彰化縣彰化市莿桐里2鄰彰鹿路35號之19",
      "COUNTY": "彰化縣",
      "TOWN": "彰化市",
      "VILLAGE": "莿桐里",
      "NEIGHBORHOOD": "2鄰",
      "ROAD": "彰鹿路",
      "SECTION": "",
      "LANE": "",
      "ALLEY": "",
      "SUB_ALLEY": "",
      "TONG": "",
      "AREA": "",
      "NUMBER": "35號之19",
      "X": 120.518521,
      "Y": 24.062470,
      "CODEBASE": "A0701-1212-00",
      "CODE1": "A0701-75-004",
      "CODE2": "A0701-75"
    }
  ]
}