{
  "Info": [
    {
      "IsSuccess": "True",
      "InAddress": "新竹縣竹北市東平里六家7路75號",
      "InSRS": "EPSG:4326",
      "InFuzzyType": "[單雙號機制]+[最近門牌號機制]",
      "InFuzzyBuffer": "0",
      "InIsOnlyFullMatch": "False",
      "InIsSupportPast": "True",
      "InIsShowCodeBase": "True",
      "InIsLockCounty": "True",
      "InIsLockTown": "False",
      "InIsLockVillage": "False",
      "InIsLockRoadSection": "False",
      "InIsLockLane": "False",
      "InIsLockAlley": "False",
      "InIsLockArea": "False",
      "InIsSameNumber_SubNumber": "True",
      "InCanIgnoreVillage": "True",
      "InCanIgnoreNeighborhood": "True",
      "InReturnMaxCount": "0",
      "OutTotal": "13",
      "OutMatchType": "模糊比對",
      "OutMatchCode": "[新竹縣]\tT:1,V:1,R:0,S:-1,L:-1,A:-1,SA:-1,T:-1,AR:-1,NO:1,E:-1,N:-1",
      "OutTraceInfo": "[新竹縣]\t { 模糊比對 } (竹北市)\t找到符合的[鄉鎮市區]，(東平里)\t找到符合的[村里]，(六家7路)\t找不到符合的[路街名]，進行轉換搜尋[街變成路，路變成街]，進行轉換搜尋[路變成地區名]，轉換搜尋找不到符合的[路街名]，(75號)\t找到符合的[門牌號碼]，進行[單號過濾]，模糊比對找到 13 筆符合的門牌地址。( 限制回傳 10 筆門牌地址 )"
    }
  ],
  "AddressList": [
    {
      "PERIOD": "",
      "FULL_ADDR": "新竹縣竹北市東平里30鄰隘口六街75號",
      "COUNTY": "新竹縣",
      "TOWN": "竹北市",
      "VILLAGE": "東平里",
      "NEIGHBORHOOD": "30鄰",
      "ROAD": "隘口六街",
      "SECTION": "",
      "LANE": "",
      "ALLEY": "",
      "SUB_ALLEY": "",
      "TONG": "",
      "AREA": "",
      "NUMBER": "75號",
      "X": 121.034291,
      "Y": 24.802752,
      "CODEBASE": "A0401-0999-00",
      "CODE1": "A0401-49-007",
      "CODE2": "A0401-49"
    },
    {
      "PERIOD": "",
      "FULL_ADDR": "新竹縣竹北市東平里7鄰六家二街75號",
      "COUNTY": "新竹縣",
      "TOWN": "竹北市",
      "VILLAGE": "東平里",
      "NEIGHBORHOOD": "7鄰",
      "ROAD": "六家二街",
      "SECTION": "",
      "LANE": "",
      "ALLEY": "",
      "SUB_ALLEY": "",
      "TONG": "",
      "AREA": "",
      "NUMBER": "75號",
      "X": 121.027162,
      "Y": 24.809477,
      "CODEBASE": "A0401-0930-00",
      "CODE1": "A0401-50-001",
      "CODE2": "A0401-50"
    },
    {
      "PERIOD": "",
      "FULL_ADDR": "新竹縣竹北市東平里7鄰嘉豐五路二段75號",
      "COUNTY": "新竹縣",
      "TOWN": "竹北市",
      "VILLAGE": "東平里",
      "NEIGHBORHOOD": "7鄰",
      "ROAD": "嘉豐五路",
      "SECTION": "2",
      "LANE": "",
      "ALLEY": "",
      "SUB_ALLEY": "",
      "TONG": "",
      "AREA": "",
      "NUMBER": "75號",
      "X": 121.026171,
      "Y": 24.809267,
      "CODEBASE": "A0401-0937-00",
      "CODE1": "A0401-50-002",
      "CODE2": "A0401-50"
    },
    {
      "PERIOD": "",
      "FULL_ADDR": "新竹縣竹北市東平里8鄰六家七路75號",
      "COUNTY": "新竹縣",
      "TOWN": "竹北市",
      "VILLAGE": "東平里",
      "NEIGHBORHOOD": "8鄰",
      "ROAD": "六家七路",
      "SECTION": "",
      "LANE": "",
      "ALLEY": "",
      "SUB_ALLEY": "",
      "TONG": "",
      "AREA": "",
      "NUMBER": "75號",
      "X": 121.026079,
      "Y": 24.808008,
      "CODEBASE": "A0401-0945-00",
      "CODE1": "A0401-50-002",
      "CODE2": "A0401-50"
    },
    {
      "PERIOD": "",
      "FULL_ADDR": "新竹縣竹北市東平里13鄰嘉豐六路二段75號",
      "COUNTY": "新竹縣",
      "TOWN": "竹北市",
      "VILLAGE": "東平里",
      "NEIGHBORHOOD": "13鄰",
      "ROAD": "嘉豐六路",
      "SECTION": "2",
      "LANE": "",
      "ALLEY": "",
      "SUB_ALLEY": "",
      "TONG": "",
      "AREA": "",
      "NUMBER": "75號",
      "X": 121.027558,
      "Y": 24.807784,
      "CODEBASE": "A0401-0958-00",
      "CODE1": "A0401-50-005",
      "CODE2": "A0401-50"
    },
    {
      "PERIOD": "",
      "FULL_ADDR": "新竹縣竹北市東平里17鄰嘉政二街75號",
      "COUNTY": "新竹縣",
      "TOWN": "竹北市",
      "VILLAGE": "東平里",
      "NEIGHBORHOOD": "17鄰",
      "ROAD": "嘉政二街",
      "SECTION": "",
      "LANE": "",
      "ALLEY": "",
      "SUB_ALLEY": "",
      "TONG": "",
      "AREA": "",
      "NUMBER": "75號",
      "X": 121.028505,
      "Y": 24.806716,
      "CODEBASE": "A0401-0963-00",
      "CODE1": "A0401-50-006",
      "CODE2": "A0401-50"
    },
    {
      "PERIOD": "",
      "FULL_ADDR": "新竹縣竹北市東平里22鄰嘉政七街75號",
      "COUNTY": "新竹縣",
      "TOWN": "竹北市",
      "VILLAGE": "東平里",
      "NEIGHBORHOOD": "22鄰",
      "ROAD": "嘉政七街",
      "SECTION": "",
      "LANE": "",
      "ALLEY": "",
      "SUB_ALLEY": "",
      "TONG": "",
      "AREA": "",
      "NUMBER": "75號",
      "X": 121.031070,
      "Y": 24.803995,
      "CODEBASE": "A0401-0991-00",
      "CODE1": "A0401-49-006",
      "CODE2": "A0401-49"
    },
    {
      "PERIOD": "",
      "FULL_ADDR": "新竹縣竹北市東平里23鄰六家一路二段75號",
      "COUNTY": "新竹縣",
      "TOWN": "竹北市",
      "VILLAGE": "東平里",
      "NEIGHBORHOOD": "23鄰",
      "ROAD": "六家一路",
      "SECTION": "2",
      "LANE": "",
      "ALLEY": "",
      "SUB_ALLEY": "",
      "TONG": "",
      "AREA": "",
      "NUMBER": "75號",
      "X": 121.034662,
      "Y": 24.806311,
      "CODEBASE": "A0401-0966-00",
      "CODE1": "A0401-49-006",
      "CODE2": "A0401-49"
    },
    {
      "PERIOD": "",
      "FULL_ADDR": "新竹縣竹北市東平里25鄰嘉豐十一路二段75號",
      "COUNTY": "新竹縣",
      "TOWN": "竹北市",
      "VILLAGE": "東平里",
      "NEIGHBORHOOD": "25鄰",
      "ROAD": "嘉豐十一路",
      "SECTION": "2",
      "LANE": "",
      "ALLEY": "",
      "SUB_ALLEY": "",
      "TONG": "",
      "AREA": "",
      "NUMBER": "75號",
      "X": 121.033460,
      "Y": 24.804977,
      "CODEBASE": "A0401-0986-00",
      "CODE1": "A0401-49-007",
      "CODE2": "A0401-49"
    },
    {
      "PERIOD": "",
      "FULL_ADDR": "新竹縣竹北市東平里27鄰興隆路五段75號",
      "COUNTY": "新竹縣",
      "TOWN": "竹北市",
      "VILLAGE": "東平里",
      "NEIGHBORHOOD": "27鄰",
      "ROAD": "興隆路",
      "SECTION": "5",
      "LANE": "",
      "ALLEY": "",
      "SUB_ALLEY": "",
      "TONG": "",
      "AREA": "",
      "NUMBER": "75號",
      "X": 121.032827,
      "Y": 24.802523,
      "CODEBASE": "A0401-0994-00",
      "CODE1": "A0401-49-007",
      "CODE2": "A0401-49"
    }
  ]
}