{
  "Info": [
    {
      "IsSuccess": "True",
      "InAddress": "桃園市桃園區東山里東山里安東街17號",
      "InSRS": "EPSG:4326",
      "InFuzzyType": "[單雙號機制]+[最近門牌號機制]",
      "InFuzzyBuffer": "0",
      "InIsOnlyFullMatch": "False",
      "InIsSupportPast": "True",
      "InIsShowCodeBase": "True",
      "InIsLockCounty": "True",
      "InIsLockTown": "False",
      "InIsLockVillage": "False",
      "InIsLockRoadSection": "False",
      "InIsLockLane": "False",
      "InIsLockAlley": "False",
      "InIsLockArea": "False",
      "InIsSameNumber_SubNumber": "True",
      "InCanIgnoreVillage": "True",
      "InCanIgnoreNeighborhood": "True",
      "InReturnMaxCount": "0",
      "OutTotal": "7",
      "OutMatchType": "模糊比對",
      "OutMatchCode": "[桃園市]\tT:1,V:1,R:0,S:-1,L:-1,A:-1,SA:-1,T:-1,AR:-1,NO:1,E:-1,N:-1",
      "OutTraceInfo": "[桃園市]\t { 模糊比對 } (桃園區)\t找到符合的[鄉鎮市區]，(東山里)\t找到符合的[村里]，(東山里安東街)\t找不到符合的[路街名]，進行轉換搜尋[街變成路，路變成街]，進行轉換搜尋[路變成地區名]，轉換搜尋找不到符合的[路街名]，(17號)\t找到符合的[門牌號碼]，進行[單號過濾]，模糊比對找到 7 筆符合的門牌地址。"
    }
  ],
  "AddressList": [
    {
      "PERIOD": "",
      "FULL_ADDR": "桃園市桃園區東山里10鄰鎮安街17號",
      "COUNTY": "桃園市",
      "TOWN": "桃園區",
      "VILLAGE": "東山里",
      "NEIGHBORHOOD": "10鄰",
      "ROAD": "鎮安街",
      "SECTION": "",
      "LANE": "",
      "ALLEY": "",
      "SUB_ALLEY": "",
      "TONG": "",
      "AREA": "",
      "NUMBER": "17號",
      "X": 121.316458,
      "Y": 24.992280,
      "CODEBASE": "A6801-1293-00",
      "CODE1": "A6801-82-004",
      "CODE2": "A6801-82"
    },
    {
      "PERIOD": "",
      "FULL_ADDR": "桃園市桃園區東山里13鄰鎮東街17號",
      "COUNTY": "桃園市",
      "TOWN": "桃園區",
      "VILLAGE": "東山里",
      "NEIGHBORHOOD": "13鄰",
      "ROAD": "鎮東街",
      "SECTION": "",
      "LANE": "",
      "ALLEY": "",
      "SUB_ALLEY": "",
      "TONG": "",
      "AREA": "",
      "NUMBER": "17號",
      "X": 121.316857,
      "Y": 24.991862,
      "CODEBASE": "A6801-1319-00",
      "CODE1": "A6801-82-007",
      "CODE2": "A6801-82"
    },
    {
      "PERIOD": "",
      "FULL_ADDR": "桃園市桃園區東山里14鄰安東街17號",
      "COUNTY": "桃園市",
      "TOWN": "桃園區",
      "VILLAGE": "東山里",
      "NEIGHBORHOOD": "14鄰",
      "ROAD": "安東街",
      "SECTION": "",
      "LANE": "",
      "ALLEY": "",
      "SUB_ALLEY": "",
      "TONG": "",
      "AREA": "",
      "NUMBER": "17號",
      "X": 121.316331,
      "Y": 24.991247,
      "CODEBASE": "A6801-1334-00",
      "CODE1": "A6801-82-006",
      "CODE2": "A6801-82"
    },
    {
      "PERIOD": "",
      "FULL_ADDR": "桃園市桃園區東山里14鄰朝陽街二段17號",
      "COUNTY": "桃園市",
      "TOWN": "桃園區",
      "VILLAGE": "東山里",
      "NEIGHBORHOOD": "14鄰",
      "ROAD": "朝陽街",
      "SECTION": "2",
      "LANE": "",
      "ALLEY": "",
      "SUB_ALLEY": "",
      "TONG": "",
      "AREA": "",
      "NUMBER": "17號",
      "X": 121.315400,
      "Y": 24.991873,
      "CODEBASE": "A6801-1334-00",
      "CODE1": "A6801-82-006",
      "CODE2": "A6801-82"
    },
    {
      "PERIOD": "",
      "FULL_ADDR": "桃園市桃園區東山里3鄰朝陽街一段17號",
      "COUNTY": "桃園市",
      "TOWN": "桃園區",
      "VILLAGE": "東山里",
      "NEIGHBORHOOD": "3鄰",
      "ROAD": "朝陽街",
      "SECTION": "1",
      "LANE": "",
      "ALLEY": "",
      "SUB_ALLEY": "",
      "TONG": "",
      "AREA": "",
      "NUMBER": "17號",
      "X": 121.314392,
      "Y": 24.992410,
      "CODEBASE": "A6801-1287-00",
      "CODE1": "A6801-76-012",
      "CODE2": "A6801-76"
    },
    {
      "PERIOD": "",
      "FULL_ADDR": "桃園市桃園區東山里4鄰鎮江街17號",
      "COUNTY": "桃園市",
      "TOWN": "桃園區",
      "VILLAGE": "東山里",
      "NEIGHBORHOOD": "4鄰",
      "ROAD": "鎮江街",
      "SECTION": "",
      "LANE": "",
      "ALLEY": "",
      "SUB_ALLEY": "",
      "TONG": "",
      "AREA": "",
      "NUMBER": "17號",
      "X": 121.314971,
      "Y": 24.993089,
      "CODEBASE": "A6801-1255-00",
      "CODE1": "A6801-76-010",
      "CODE2": "A6801-76"
    },
    {
      "PERIOD": "",
      "FULL_ADDR": "桃園市桃園區東山里6鄰安樂街17號",
      "COUNTY": "桃園市",
      "TOWN": "桃園區",
      "VILLAGE": "東山里",
      "NEIGHBORHOOD": "6鄰",
      "ROAD": "安樂街",
      "SECTION": "",
      "LANE": "",
      "ALLEY": "",
      "SUB_ALLEY": "",
      "TONG": "",
      "AREA": "",
      "NUMBER": "17號",
      "X": 121.315076,
      "Y": 24.992211,
      "CODEBASE": "A6801-1291-00",
      "CODE1": "A6801-76-013",
      "CODE2": "A6801-76"
    }
  ]
}